[
  {
    "id": 16,
    "owner_address": "AT69EQXs46PT21TUb46RC9BA6zUAziRMGahYGWaaPHMp",
    "v2ex_username": null,
    "avatar_url": null,
    "token_address": "9raUVuzeWUk53co63M4WXLWPWE4Xc6Lpn7RS9dnkpump",
    "token_account_address": "5FDXBoVaJLzNVEHS5todiwRxrbhfnCmP8ryyLSF8bfhv",
    "hold_rank": 12,
    "hold_amount": 3527139.346745,
    "decimals": 6,
    "rank_delta": 0,
    "hold_percentage": 0.3527139346745,
    "checked_at": "2025-11-18 16:31:03",
    "amount_delta": 3531.048563
  },
  {
    "id": 36,
    "owner_address": "DVigwYGtjNxyCN7uFJThsnqkf8coiynoayArDp9jrCNL",
    "v2ex_username": null,
    "avatar_url": null,
    "token_address": "9raUVuzeWUk53co63M4WXLWPWE4Xc6Lpn7RS9dnkpump",
    "token_account_address": "49Zhb79rEMd6xNiP47xLd7b9tMxmTBLMP8JTRBG5uCSi",
    "hold_rank": 23,
    "hold_amount": 1881040.963395,
    "decimals": 6,
    "rank_delta": 5,
    "hold_percentage": 0.18810409633949998,
    "checked_at": "2025-11-18 07:00:19",
    "amount_delta": 507210.681742
  },
  {
    "id": 26,
    "owner_address": "GmV3rphF8VmiHr7TESBEMpSXr2vtyfm8E9DeHG4dRCKe",
    "v2ex_username": null,
    "avatar_url": null,
    "token_address": "9raUVuzeWUk53co63M4WXLWPWE4Xc6Lpn7RS9dnkpump",
    "token_account_address": "FSc7j2GLdjacFcnW3zibcuVGCSXVFG1cFXa93gmeXzcB",
    "hold_rank": 25,
    "hold_amount": 1732601,
    "decimals": 6,
    "rank_delta": -2,
    "hold_percentage": 0.1732601,
    "checked_at": "2025-11-18 16:01:06",
    "amount_delta": 0
  },
  {
    "id": 23,
    "owner_address": "D4MjzBu1GxzEiUPE97J2Enc1XJ6xaNLS6CZCAt2af1Hj",
    "v2ex_username": null,
    "avatar_url": null,
    "token_address": "9raUVuzeWUk53co63M4WXLWPWE4Xc6Lpn7RS9dnkpump",
    "token_account_address": "EqD8aBeDHKvVxa3NKQF4hGi2NXQUtX8Yj2ofZWMQuANg",
    "hold_rank": 26,
    "hold_amount": 1655057.722125,
    "decimals": 6,
    "rank_delta": -1,
    "hold_percentage": 0.16550577221249999,
    "checked_at": "2025-11-18 07:00:19",
    "amount_delta": 0
  },
  {
    "id": 33,
    "owner_address": "Do7veVEUFoPWUZfBDstEniM25uw5TubMTeJ7W2vqEEcD",
    "v2ex_username": null,
    "avatar_url": null,
    "token_address": "9raUVuzeWUk53co63M4WXLWPWE4Xc6Lpn7RS9dnkpump",
    "token_account_address": "ARMCPHCSwrmuLGrdVmW43iTR3SVjT4aDb1LzR5BNvYwT",
    "hold_rank": 31,
    "hold_amount": 1149834.080465,
    "decimals": 6,
    "rank_delta": 1,
    "hold_percentage": 0.11498340804650001,
    "checked_at": "2025-11-18 03:00:31",
    "amount_delta": 0
  },
  {
    "id": 34,
    "owner_address": "EabEqYf3h31MthfGPSMRGBuSoNrBbZ6ZE7YgcBZWu5MP",
    "v2ex_username": null,
    "avatar_url": null,
    "token_address": "9raUVuzeWUk53co63M4WXLWPWE4Xc6Lpn7RS9dnkpump",
    "token_account_address": "J6RHYM1gV2HFDSGqBjYbyKZBqjD4HBr2Tni3by6J3YmY",
    "hold_rank": 32,
    "hold_amount": 1149353.291804,
    "decimals": 6,
    "rank_delta": 1,
    "hold_percentage": 0.11493532918039999,
    "checked_at": "2025-11-18 03:00:31",
    "amount_delta": 0
  },
  {
    "id": 63,
    "owner_address": "BYS2b1FGbYAd12EBz6Ln88Kg81aQD3htyhzN8g8aN8R7",
    "v2ex_username": null,
    "avatar_url": null,
    "token_address": "9raUVuzeWUk53co63M4WXLWPWE4Xc6Lpn7RS9dnkpump",
    "token_account_address": "8ouQvbfntmwtLMqGBuNgiW1QV7jk7DzQ5yp91brGYMGS",
    "hold_rank": 33,
    "hold_amount": 1090764.326339,
    "decimals": 6,
    "rank_delta": 1,
    "hold_percentage": 0.1090764326339,
    "checked_at": "2025-11-18 03:00:31",
    "amount_delta": 0
  },
  {
    "id": 78,
    "owner_address": "FKwSPeNs3Tqtd1auZYjHT8UJEquix2E7K3DX2HfKHSdP",
    "v2ex_username": null,
    "avatar_url": null,
    "token_address": "9raUVuzeWUk53co63M4WXLWPWE4Xc6Lpn7RS9dnkpump",
    "token_account_address": "DarGgtMRZteRcZLYjvyEFkxUZ2ZCnkJkqL5UjQszoD68",
    "hold_rank": 34,
    "hold_amount": 1084804.360741,
    "decimals": 6,
    "rank_delta": 1,
    "hold_percentage": 0.1084804360741,
    "checked_at": "2025-11-18 03:00:31",
    "amount_delta": 0
  },
  {
    "id": 38,
    "owner_address": "HR8Yvqw5MEV2zxDcNsB2czEFNPeR8kUyM9JeNxHoFRsg",
    "v2ex_username": null,
    "avatar_url": null,
    "token_address": "9raUVuzeWUk53co63M4WXLWPWE4Xc6Lpn7RS9dnkpump",
    "token_account_address": "9siHHiwe5xhk1Mz2rMbLkA9FbJu9Jeau1cFJz3VropTQ",
    "hold_rank": 36,
    "hold_amount": 1040951.716958,
    "decimals": 6,
    "rank_delta": 1,
    "hold_percentage": 0.10409517169579999,
    "checked_at": "2025-11-18 03:00:31",
    "amount_delta": 0
  },
  {
    "id": 151404,
    "owner_address": "CsgyBPBiwjN9g53sDFyat9mzknM1ZjmrT8gGby4SCxVC",
    "v2ex_username": null,
    "avatar_url": null,
    "token_address": "9raUVuzeWUk53co63M4WXLWPWE4Xc6Lpn7RS9dnkpump",
    "token_account_address": "5tXsZNr3JWL6s1A6rmvYarKzmADa7UVFA1nK7DA3ki53",
    "hold_rank": 39,
    "hold_amount": 1002299.840892,
    "decimals": 6,
    "rank_delta": 1,
    "hold_percentage": 0.1002299840892,
    "checked_at": "2025-11-18 03:00:31",
    "amount_delta": 0
  },
  {
    "id": 40,
    "owner_address": "BXJ7gdmP2Yz2sk2StnureXvhALuGEPsdMvDGyx9AgT1H",
    "v2ex_username": null,
    "avatar_url": null,
    "token_address": "9raUVuzeWUk53co63M4WXLWPWE4Xc6Lpn7RS9dnkpump",
    "token_account_address": "A1x31Pn6wQmxhteVUpumrqdwispAsWA7fHTQDkY6FF5U",
    "hold_rank": 42,
    "hold_amount": 960285.41652,
    "decimals": 6,
    "rank_delta": 1,
    "hold_percentage": 0.096028541652,
    "checked_at": "2025-11-18 03:00:31",
    "amount_delta": 0
  },
  {
    "id": 41,
    "owner_address": "BJoaVrmMmvWa4QKnSnVqkSmMkBkZzYjq4mrNH61sFCJB",
    "v2ex_username": null,
    "avatar_url": null,
    "token_address": "9raUVuzeWUk53co63M4WXLWPWE4Xc6Lpn7RS9dnkpump",
    "token_account_address": "ErHaiyEKWUgXyLecBN7hoF5DZXY3BhFstwTT59K18izx",
    "hold_rank": 43,
    "hold_amount": 953388.833799,
    "decimals": 6,
    "rank_delta": 1,
    "hold_percentage": 0.0953388833799,
    "checked_at": "2025-11-18 03:00:31",
    "amount_delta": 0
  },
  {
    "id": 43,
    "owner_address": "DiDpcxgdBDwfDV7qSTXXhK3KWEZkaeNKd1irJFP3XSFd",
    "v2ex_username": null,
    "avatar_url": null,
    "token_address": "9raUVuzeWUk53co63M4WXLWPWE4Xc6Lpn7RS9dnkpump",
    "token_account_address": "8KuLzZfFhifBG1B3MxZQfQpGqfkNQNogmwTZpnk7CYag",
    "hold_rank": 45,
    "hold_amount": 894536.23154,
    "decimals": 6,
    "rank_delta": 1,
    "hold_percentage": 0.089453623154,
    "checked_at": "2025-11-18 03:00:31",
    "amount_delta": 0
  },
  {
    "id": 18406,
    "owner_address": "J9hG3kcXRqW4GSts2Dnh8emYPT7JXY1jdNFvNx8cfiQ5",
    "v2ex_username": null,
    "avatar_url": null,
    "token_address": "9raUVuzeWUk53co63M4WXLWPWE4Xc6Lpn7RS9dnkpump",
    "token_account_address": "6Q6FDZJHwN9JTrasKMmQjgToENMxUD9LvGKk92zNSuB7",
    "hold_rank": 47,
    "hold_amount": 845563.415851,
    "decimals": 6,
    "rank_delta": 1,
    "hold_percentage": 0.0845563415851,
    "checked_at": "2025-11-18 03:00:31",
    "amount_delta": 0
  },
  {
    "id": 23087,
    "owner_address": "BUSzqL3C9B8afLRo9JkmmkMidoHQmmwd9Mr8Kxf5bsmm",
    "v2ex_username": null,
    "avatar_url": null,
    "token_address": "9raUVuzeWUk53co63M4WXLWPWE4Xc6Lpn7RS9dnkpump",
    "token_account_address": "7dhho3PqtcWVB8amL4BcDk3uBUMeY3ZNHriXysKZgmVD",
    "hold_rank": 48,
    "hold_amount": 844778,
    "decimals": 6,
    "rank_delta": 1,
    "hold_percentage": 0.0844778,
    "checked_at": "2025-11-18 03:00:31",
    "amount_delta": 0
  },
  {
    "id": 50,
    "owner_address": "DciYZLbcpcHrNDhKbdsNGYPV5rw6TSknWASaKABATNwX",
    "v2ex_username": null,
    "avatar_url": null,
    "token_address": "9raUVuzeWUk53co63M4WXLWPWE4Xc6Lpn7RS9dnkpump",
    "token_account_address": "4dXiZVdqBGoV5Zp7uNYG8v9RdRNNapQyfbhhStDm7Qxo",
    "hold_rank": 50,
    "hold_amount": 814449.622543,
    "decimals": 6,
    "rank_delta": 1,
    "hold_percentage": 0.0814449622543,
    "checked_at": "2025-11-18 03:00:31",
    "amount_delta": 0
  },
  {
    "id": 51,
    "owner_address": "WSvzsUSSuAaTut8xeBgTY1Xeo5pkcVRwVzMB9nQc5qf",
    "v2ex_username": null,
    "avatar_url": null,
    "token_address": "9raUVuzeWUk53co63M4WXLWPWE4Xc6Lpn7RS9dnkpump",
    "token_account_address": "9WvY8bejehMoDU2Y5fxLukHM9wwBhBgkPJaXBmHUBCWi",
    "hold_rank": 51,
    "hold_amount": 812542.07663,
    "decimals": 6,
    "rank_delta": 1,
    "hold_percentage": 0.081254207663,
    "checked_at": "2025-11-18 03:00:32",
    "amount_delta": 0
  },
  {
    "id": 57,
    "owner_address": "GQjBHAGZtJtdGtbYrorwYanuursT1KcZcvPznqEPdJ7t",
    "v2ex_username": null,
    "avatar_url": null,
    "token_address": "9raUVuzeWUk53co63M4WXLWPWE4Xc6Lpn7RS9dnkpump",
    "token_account_address": "5HNVPXKkPEoZGvizoe2um68Rh9mooK7CrR4ZdKvMz6qR",
    "hold_rank": 57,
    "hold_amount": 701890.275288,
    "decimals": 6,
    "rank_delta": 1,
    "hold_percentage": 0.0701890275288,
    "checked_at": "2025-11-18 03:00:32",
    "amount_delta": 0
  },
  {
    "id": 58,
    "owner_address": "CisTDiDKbz6cye5B6TtEgKUCqmBcHg5vfTxxVwwJAzVy",
    "v2ex_username": null,
    "avatar_url": null,
    "token_address": "9raUVuzeWUk53co63M4WXLWPWE4Xc6Lpn7RS9dnkpump",
    "token_account_address": "38ikR6Jy8PpN1soCcKpqizYj7Emx21RBq2tPFxzHRpfL",
    "hold_rank": 58,
    "hold_amount": 696294.607037,
    "decimals": 6,
    "rank_delta": 1,
    "hold_percentage": 0.06962946070369999,
    "checked_at": "2025-11-18 03:00:32",
    "amount_delta": 0
  },
  {
    "id": 59,
    "owner_address": "RpnwDF4uTXtR8p9aea9cgYq7W5euPPtjTCpEZ66mBLw",
    "v2ex_username": null,
    "avatar_url": null,
    "token_address": "9raUVuzeWUk53co63M4WXLWPWE4Xc6Lpn7RS9dnkpump",
    "token_account_address": "SKe2pFSfTh6Qahd8FUunsuFLQjBoWk3v4LWwPHHjzMr",
    "hold_rank": 60,
    "hold_amount": 682602.87133,
    "decimals": 6,
    "rank_delta": 1,
    "hold_percentage": 0.068260287133,
    "checked_at": "2025-11-18 03:00:32",
    "amount_delta": 0
  },
  {
    "id": 71,
    "owner_address": "H5uYBn9MSrMTEz9deLDGBe9eczsfzXjZjX1xVcB6FJgU",
    "v2ex_username": null,
    "avatar_url": null,
    "token_address": "9raUVuzeWUk53co63M4WXLWPWE4Xc6Lpn7RS9dnkpump",
    "token_account_address": "4KbSRsxHg3Kz9uo6S6NMjb1CY6X8wDPZgwzrg2S9PARy",
    "hold_rank": 62,
    "hold_amount": 656653.936615,
    "decimals": 6,
    "rank_delta": 1,
    "hold_percentage": 0.0656653936615,
    "checked_at": "2025-11-18 10:30:16",
    "amount_delta": 70
  },
  {
    "id": 104344,
    "owner_address": "Egebx7TUpeqk6qJqqv8zVUy1iV6Tj3huwcfyRcG9XmML",
    "v2ex_username": null,
    "avatar_url": null,
    "token_address": "9raUVuzeWUk53co63M4WXLWPWE4Xc6Lpn7RS9dnkpump",
    "token_account_address": "htDzGHNCpvGEsdw4GUsZ8TNPXqxGKkfJgNH9nvRzUS1",
    "hold_rank": 63,
    "hold_amount": 653478.568754,
    "decimals": 6,
    "rank_delta": 1,
    "hold_percentage": 0.0653478568754,
    "checked_at": "2025-11-18 03:00:32",
    "amount_delta": 0
  },
  {
    "id": 67,
    "owner_address": "Q1dnca4eCDC6gNffGERvCWYn2JSjG6tYurLmv8ENugv",
    "v2ex_username": null,
    "avatar_url": null,
    "token_address": "9raUVuzeWUk53co63M4WXLWPWE4Xc6Lpn7RS9dnkpump",
    "token_account_address": "DrbzF4FzGqvyxhfevAUUB9dRvFNt9VNJSKyYof2u7azk",
    "hold_rank": 67,
    "hold_amount": 585163.462778,
    "decimals": 6,
    "rank_delta": 1,
    "hold_percentage": 0.0585163462778,
    "checked_at": "2025-11-18 03:00:32",
    "amount_delta": 0
  },
  {
    "id": 73,
    "owner_address": "F2zkDG4tLZ4oFPGyYiX5ffTobvM1Av2zDwweCgVtP1qS",
    "v2ex_username": null,
    "avatar_url": null,
    "token_address": "9raUVuzeWUk53co63M4WXLWPWE4Xc6Lpn7RS9dnkpump",
    "token_account_address": "HH41uSXaoGYptTUxkSvH6N1E9hHq5pvGP8pbQfCqo4PH",
    "hold_rank": 71,
    "hold_amount": 510001,
    "decimals": 6,
    "rank_delta": 1,
    "hold_percentage": 0.05100010000000001,
    "checked_at": "2025-11-18 03:00:32",
    "amount_delta": 0
  },
  {
    "id": 74,
    "owner_address": "GxH37UocCZuWMj62do6fp7zFbugqb4bJ5DSqkxNMnaGe",
    "v2ex_username": null,
    "avatar_url": null,
    "token_address": "9raUVuzeWUk53co63M4WXLWPWE4Xc6Lpn7RS9dnkpump",
    "token_account_address": "9W1456jutVbpFTZKBYqYPfw5m2iMmvDFS9FfviWtbqG2",
    "hold_rank": 72,
    "hold_amount": 506666.23605,
    "decimals": 6,
    "rank_delta": 1,
    "hold_percentage": 0.050666623604999995,
    "checked_at": "2025-11-18 03:00:32",
    "amount_delta": 0
  },
  {
    "id": 80,
    "owner_address": "ayPGEt9RCF3pTBnt3FDDVYUtPDHhLu6G9Pk7kY2xrnF",
    "v2ex_username": null,
    "avatar_url": null,
    "token_address": "9raUVuzeWUk53co63M4WXLWPWE4Xc6Lpn7RS9dnkpump",
    "token_account_address": "AD1dfRAw6GJJ4hDQBHD2DxRhbUxAKyv3nVDCAGm6QZhP",
    "hold_rank": 79,
    "hold_amount": 454240.908207,
    "decimals": 6,
    "rank_delta": 1,
    "hold_percentage": 0.0454240908207,
    "checked_at": "2025-11-18 03:00:32",
    "amount_delta": 0
  },
  {
    "id": 84,
    "owner_address": "GuDPvXrmiCyFS1VTgm3dsEfPcuQ2NZZjZemCctgpx6wn",
    "v2ex_username": null,
    "avatar_url": null,
    "token_address": "9raUVuzeWUk53co63M4WXLWPWE4Xc6Lpn7RS9dnkpump",
    "token_account_address": "CaawDgm8rrrPQJsaEV6H1GKd72xbVcVpAEvXhhaFGnnD",
    "hold_rank": 83,
    "hold_amount": 435984.523248,
    "decimals": 6,
    "rank_delta": 1,
    "hold_percentage": 0.0435984523248,
    "checked_at": "2025-11-18 03:00:32",
    "amount_delta": 0
  },
  {
    "id": 85,
    "owner_address": "J9yGjossKspT8WKXMkyvzHhPkwCAPAQuJarJ6yrKkczZ",
    "v2ex_username": null,
    "avatar_url": null,
    "token_address": "9raUVuzeWUk53co63M4WXLWPWE4Xc6Lpn7RS9dnkpump",
    "token_account_address": "66Kr8ULjXf5sX8m9SDqgpLfe9YLcTngbJFA9zFyThVHx",
    "hold_rank": 84,
    "hold_amount": 428746.652896,
    "decimals": 6,
    "rank_delta": 1,
    "hold_percentage": 0.042874665289599996,
    "checked_at": "2025-11-18 03:00:32",
    "amount_delta": 0
  },
  {
    "id": 87,
    "owner_address": "hnV9VhLB6ED7qY9vzDT3qj7Se4acrFgd1Na5GRDv2ex",
    "v2ex_username": null,
    "avatar_url": null,
    "token_address": "9raUVuzeWUk53co63M4WXLWPWE4Xc6Lpn7RS9dnkpump",
    "token_account_address": "E44UAgddtKd1bEA4eWDFSzJy1Xe5egnFsC67sussMCTp",
    "hold_rank": 85,
    "hold_amount": 425914.706463,
    "decimals": 6,
    "rank_delta": 1,
    "hold_percentage": 0.042591470646300006,
    "checked_at": "2025-11-18 03:00:32",
    "amount_delta": 0
  },
  {
    "id": 117,
    "owner_address": "N4SsBhJG5vVAS25WLaZS5kxuJfXTsWCHqhrk3BSdwvR",
    "v2ex_username": null,
    "avatar_url": null,
    "token_address": "9raUVuzeWUk53co63M4WXLWPWE4Xc6Lpn7RS9dnkpump",
    "token_account_address": "G8WYaZsLMKB7pog47Y6f18HQT6vcGqf8ejZoU3VBnu2e",
    "hold_rank": 89,
    "hold_amount": 403412.685835,
    "decimals": 6,
    "rank_delta": 1,
    "hold_percentage": 0.0403412685835,
    "checked_at": "2025-11-18 03:00:32",
    "amount_delta": 0
  },
  {
    "id": 179160,
    "owner_address": "DMweKdMZFKFRtx2w6awzUFyTok9ZvGLY58TMrrLaMREg",
    "v2ex_username": null,
    "avatar_url": null,
    "token_address": "9raUVuzeWUk53co63M4WXLWPWE4Xc6Lpn7RS9dnkpump",
    "token_account_address": "8cijaTe927nUfD8Lpm2JLBFPbrzjxS82onNoCGYSBZh4",
    "hold_rank": 120,
    "hold_amount": 272305.924409,
    "decimals": 6,
    "rank_delta": 0,
    "hold_percentage": 0.027230592440900002,
    "checked_at": "2025-11-18 03:00:32",
    "amount_delta": 0
  }
]